dconfig/__init__.py
dconfig/admin.py
dconfig/installer.py
dconfig/models.py
dconfig/test_settings.py
dconfig/tests.py
dconfig/views.py
dconfig/files/__init__.py
dconfig/files/auto_settings.py
dconfig/files/common_settings.py
dconfig/files/configs.py.default
dconfig/files/context_processors.py
dconfig/files/fabfile.py
dconfig/files/gitignore
dconfig/files/kube_init.sh
dconfig/files/requirements.txt
dconfig/files/rest_exception_handler.py
dconfig/files/settings.py
dconfig/files/uwsgi.ini
dconfig/files/auto_setting_modules/__init__.py
dconfig/files/auto_setting_modules/celery/__init__.py
dconfig/files/auto_setting_modules/celery/package.py
dconfig/files/auto_setting_modules/celery/settings.py
dconfig/files/auto_setting_modules/cors_headers/__init__.py
dconfig/files/auto_setting_modules/cors_headers/package.py
dconfig/files/auto_setting_modules/cors_headers/settings.py
dconfig/files/auto_setting_modules/picker/__init__.py
dconfig/files/auto_setting_modules/picker/package.py
dconfig/files/auto_setting_modules/picker/settings.py
dconfig/files/auto_setting_modules/rest_framework/__init__.py
dconfig/files/auto_setting_modules/rest_framework/package.py
dconfig/files/auto_setting_modules/rest_framework/settings.py
dconfig/files/auto_setting_modules/sass_processor/__init__.py
dconfig/files/auto_setting_modules/sass_processor/package.py
dconfig/files/auto_setting_modules/sass_processor/settings.py
dconfig/files/auto_setting_modules/sentry_sdk/__init__.py
dconfig/files/auto_setting_modules/sentry_sdk/package.py
dconfig/files/auto_setting_modules/sentry_sdk/settings.py
dconfig/files/media/gitignore
dconfig/files/static/gitignore
dconfig/files/utils/__init__.py
dconfig/files/utils/configs_loader.py
dconfig/files/utils/decorators.py
dconfig/files/utils/misc.py
dconfig/files/utils/rest_views.py
dconfig/management/__init__.py
dconfig/management/commands/__init__.py
dconfig/management/commands/conf.py
dconfig/management/commands/install.py
dconfig/migrations/__init__.py
dconfig-1.5.0.dist-info/AUTHORS
dconfig-1.5.0.dist-info/LICENSE
dconfig-1.5.0.dist-info/METADATA
dconfig-1.5.0.dist-info/WHEEL
dconfig-1.5.0.dist-info/top_level.txt
dconfig-1.5.0.dist-info/RECORD
