Metadata-Version: 2.1
Name: dconfig
Version: 1.5.0
Summary: A Django config for the Django framework.
Home-page: https://github.com/shinznatkid/django-config
Author: Shinz Natkid
Author-email: shinznatkid@gmail.com
License: UNKNOWN
Platform: UNKNOWN
Classifier: Development Status :: 4 - Beta
Classifier: Environment :: Console
Classifier: Environment :: Web Environment
Classifier: Framework :: Django
Classifier: Intended Audience :: Developers
Classifier: Intended Audience :: System Administrators
Classifier: License :: OSI Approved :: MIT License
Classifier: Operating System :: MacOS :: MacOS X
Classifier: Operating System :: Microsoft
Classifier: Operating System :: POSIX
Classifier: Programming Language :: Python
Classifier: Topic :: Internet :: WWW/HTTP
Classifier: Topic :: Internet :: WWW/HTTP :: Dynamic Content
